iree_compiler.egg-info/top_level.txt
iree_compiler.egg-info/SOURCES.txt
iree_compiler.egg-info/entry_points.txt
iree_compiler.egg-info/dependency_links.txt
iree_compiler.egg-info/PKG-INFO
iree_compiler.egg-info/not-zip-safe
iree_compiler.egg-info/requires.txt
iree_compiler-20241104.1068.dist-info/top_level.txt
iree_compiler-20241104.1068.dist-info/RECORD
iree_compiler-20241104.1068.dist-info/entry_points.txt
iree_compiler-20241104.1068.dist-info/METADATA
iree_compiler-20241104.1068.dist-info/WHEEL
iree/build/__main__.py
iree/build/executor.py
iree/build/compile_actions.py
iree/build/metadata.py
iree/build/target_machine.py
iree/build/args.py
iree/build/onnx_actions.py
iree/build/lang.py
iree/build/main.py
iree/build/__init__.py
iree/build/net_actions.py
iree/compiler/tflite.py
iree/compiler/ir.py
iree/compiler/_package_test.py
iree/compiler/version.py
iree/compiler/tf.py
iree/compiler/passmanager.py
iree/compiler/__init__.py
iree/compiler/rewrite.py
iree/compiler/tools/binaries.py
iree/compiler/tools/tflite.py
iree/compiler/tools/core.py
iree/compiler/tools/debugging.py
iree/compiler/tools/tf.py
iree/compiler/tools/__init__.py
iree/compiler/tools/scripts/iree_opt/__main__.py
iree/compiler/tools/scripts/iree_compile/__main__.py
iree/compiler/tools/import_onnx/__main__.py
iree/compiler/tools/ir_tool/__main__.py
iree/compiler/dialects/hal.py
iree/compiler/dialects/_pdl_ops_gen.py
iree/compiler/dialects/arith.py
iree/compiler/dialects/pdl.py
iree/compiler/dialects/_iree_structured_transform_ops_gen.py
iree/compiler/dialects/util.py
iree/compiler/dialects/_llvm_ops_gen.py
iree/compiler/dialects/_gpu_ops_gen.py
iree/compiler/dialects/_structured_transform_ops_gen.py
iree/compiler/dialects/_memref_ops_gen.py
iree/compiler/dialects/_hal_ops_gen.py
iree/compiler/dialects/_shape_ops_gen.py
iree/compiler/dialects/_stream_ops_gen.py
iree/compiler/dialects/_ods_common.py
iree/compiler/dialects/iree_input.py
iree/compiler/dialects/_iree_structured_transform_ops_ext.py
iree/compiler/dialects/_amdgpu_enum_gen.py
iree/compiler/dialects/_tosa_ops_gen.py
iree/compiler/dialects/math.py
iree/compiler/dialects/_func_ops_gen.py
iree/compiler/dialects/vector.py
iree/compiler/dialects/iree_gpu.py
iree/compiler/dialects/_util_enum_gen.py
iree/compiler/dialects/amdgpu.py
iree/compiler/dialects/_iree_input_ops_gen.py
iree/compiler/dialects/_util_ops_gen.py
iree/compiler/dialects/_linalg_enum_gen.py
